airosentris/__init__.py
airosentris/agent/Agent.py
airosentris/agent/__init__.py
airosentris/algorithm/__init__.py
airosentris/algorithm/BERT/BERTRunner.py
airosentris/algorithm/BERT/BERTTrainer.py
airosentris/algorithm/BERT/MetricsCallback.py
airosentris/algorithm/BERT/__init__.py
airosentris/algorithm/BERT/resource/__init__.py
airosentris/algorithm/LLM/LLMRunner.py
airosentris/algorithm/LLM/LLMTrainer.py
airosentris/algorithm/LLM/__init__.py
airosentris/algorithm/OPENAI/OpenAIRunner.py
airosentris/algorithm/OPENAI/OpenAITrainer.py
airosentris/algorithm/OPENAI/__init__.py
airosentris/auth/Auth.py
airosentris/auth/__init__.py
airosentris/client/APIClient.py
airosentris/client/RabbitMQClient.py
airosentris/client/__init__.py
airosentris/config/ConfigFetcher.py
airosentris/config/__init__.py
airosentris/crawler/CrawlerEngine.py
airosentris/crawler/__init__.py
airosentris/crawler/apify/ApifyCrawler.py
airosentris/crawler/apify/ApifyCrawlerInstagram.py
airosentris/crawler/apify/__init__.py
airosentris/crawler/graphapi/__init__.py
airosentris/crawler/httprequest/HttpRequestCrawler.py
airosentris/crawler/httprequest/HttpRequestCrawlerCIS.py
airosentris/crawler/httprequest/__init__.py
airosentris/crawler/instaloader/__init__.py
airosentris/crawler/selenium/__init__.py
airosentris/crawler/tweepy/TweepyCrawler.py
airosentris/crawler/tweepy/TweepyCrawlerTwitter.py
airosentris/crawler/tweepy/__init__.py
airosentris/dataset/__init__.py
airosentris/dataset/airosentris_comment.py
airosentris/dataset/social_comment.py
airosentris/hardware/SystemInfo.py
airosentris/hardware/__init__.py
airosentris/logger/Logger.py
airosentris/logger/RabbitMQLogger.py
airosentris/logger/TrainerLogger.py
airosentris/logger/__init__.py
airosentris/message/AgentStatus.py
airosentris/message/Comment.py
airosentris/message/TrainParams.py
airosentris/message/__init__.py
airosentris/projects/Project.py
airosentris/projects/__init__.py
airosentris/runner/BaseRunner.py
airosentris/runner/Runner.py
airosentris-0.1.31.dist-info/LICENSE
airosentris-0.1.31.dist-info/METADATA
airosentris-0.1.31.dist-info/WHEEL
airosentris-0.1.31.dist-info/top_level.txt
airosentris-0.1.31.dist-info/RECORD
