Metadata-Version: 2.1
Name: airosentris
Version: 0.1.31
Summary: A sentiment analysis platform with AI runner and trainer components
Home-page: https://gitlab.com/sindika/project/airosentris/airosentris-python-lib
Author: Willy Achmat Fauzi
Author-email: willy.achmat@gmail.com
License: MIT
Classifier: Programming Language :: Python :: 3
Classifier: License :: OSI Approved :: MIT License
Classifier: Operating System :: OS Independent
Requires-Python: >=3.6
License-File: LICENSE
Requires-Dist: accelerate==1.1.1
Requires-Dist: aiohappyeyeballs==2.4.3
Requires-Dist: aiohttp==3.11.6
Requires-Dist: aiosignal==1.3.1
Requires-Dist: annotated-types==0.7.0
Requires-Dist: anyio==4.6.2.post1
Requires-Dist: apify-client==1.8.1
Requires-Dist: apify-shared==1.1.2
Requires-Dist: argon2-cffi==23.1.0
Requires-Dist: argon2-cffi-bindings==21.2.0
Requires-Dist: asttokens==3.0.0
Requires-Dist: async-timeout==4.0.3
Requires-Dist: attrs==24.2.0
Requires-Dist: backports.tarfile==1.2.0
Requires-Dist: certifi==2024.8.30
Requires-Dist: cffi==1.17.1
Requires-Dist: charset-normalizer==3.4.0
Requires-Dist: click==8.1.7
Requires-Dist: colorama==0.4.6
Requires-Dist: coloredlogs==15.0.1
Requires-Dist: comm==0.2.2
Requires-Dist: datasets==3.1.0
Requires-Dist: debugpy==1.8.9
Requires-Dist: decorator==5.1.1
Requires-Dist: dill==0.3.8
Requires-Dist: distro==1.9.0
Requires-Dist: docutils==0.21.2
Requires-Dist: emoji==2.14.0
Requires-Dist: evaluate==0.4.3
Requires-Dist: exceptiongroup==1.2.2
Requires-Dist: executing==2.1.0
Requires-Dist: filelock==3.16.1
Requires-Dist: flatbuffers==24.3.25
Requires-Dist: frozenlist==1.5.0
Requires-Dist: fsspec==2024.9.0
Requires-Dist: GPUtil==1.4.0
Requires-Dist: greenlet==3.1.1
Requires-Dist: groq==0.12.0
Requires-Dist: h11==0.14.0
Requires-Dist: httpcore==1.0.6
Requires-Dist: httpx==0.27.2
Requires-Dist: huggingface-hub==0.26.2
Requires-Dist: humanfriendly==10.0
Requires-Dist: idna==3.10
Requires-Dist: importlib-metadata==8.5.0
Requires-Dist: iniconfig==2.0.0
Requires-Dist: ipykernel==6.29.5
Requires-Dist: ipython==8.30.0
Requires-Dist: jaraco.classes==3.4.0
Requires-Dist: jaraco.context==6.0.1
Requires-Dist: jaraco.functools==4.1.0
Requires-Dist: jedi==0.19.2
Requires-Dist: Jinja2==3.1.4
Requires-Dist: joblib==1.4.2
Requires-Dist: jsonpatch==1.33
Requires-Dist: jsonpointer==3.0.0
Requires-Dist: jupyter-client==8.6.3
Requires-Dist: jupyter-core==5.7.2
Requires-Dist: keyring==25.5.0
Requires-Dist: langchain==0.3.8
Requires-Dist: langchain-core==0.3.21
Requires-Dist: langchain-groq==0.2.1
Requires-Dist: langchain-huggingface==0.1.2
Requires-Dist: langchain-text-splitters==0.3.2
Requires-Dist: langsmith==0.1.145
Requires-Dist: markdown-it-py==3.0.0
Requires-Dist: MarkupSafe==3.0.2
Requires-Dist: matplotlib-inline==0.1.7
Requires-Dist: mdurl==0.1.2
Requires-Dist: minio==7.2.12
Requires-Dist: more-itertools==10.5.0
Requires-Dist: mpmath==1.3.0
Requires-Dist: multidict==6.1.0
Requires-Dist: multiprocess==0.70.16
Requires-Dist: nest-asyncio==1.6.0
Requires-Dist: networkx==3.4.2
Requires-Dist: nh3==0.2.19
Requires-Dist: nltk==3.9.1
Requires-Dist: numpy==1.26.4
Requires-Dist: oauthlib==3.2.2
Requires-Dist: onnx==1.17.0
Requires-Dist: onnxruntime==1.20.0
Requires-Dist: optimum==1.23.3
Requires-Dist: orjson==3.10.12
Requires-Dist: outcome==1.3.0.post0
Requires-Dist: packaging==24.2
Requires-Dist: pandas==2.2.3
Requires-Dist: parso==0.8.4
Requires-Dist: pika==1.3.2
Requires-Dist: pillow==11.0.0
Requires-Dist: pkginfo==1.11.2
Requires-Dist: platformdirs==4.3.6
Requires-Dist: pluggy==1.5.0
Requires-Dist: prompt-toolkit==3.0.48
Requires-Dist: propcache==0.2.0
Requires-Dist: protobuf==5.28.3
Requires-Dist: psutil==6.0.0
Requires-Dist: pure-eval==0.2.3
Requires-Dist: py-cpuinfo==9.0.0
Requires-Dist: pyarrow==18.0.0
Requires-Dist: pycparser==2.22
Requires-Dist: pycryptodome==3.21.0
Requires-Dist: pydantic==2.10.1
Requires-Dist: pydantic-core==2.27.1
Requires-Dist: Pygments==2.18.0
Requires-Dist: pyreadline3==3.5.4
Requires-Dist: PySocks==1.7.1
Requires-Dist: pytest==8.3.4
Requires-Dist: python-dateutil==2.9.0.post0
Requires-Dist: python-dotenv==1.0.1
Requires-Dist: pytz==2024.2
Requires-Dist: PyYAML==6.0.2
Requires-Dist: pyzmq==26.2.0
Requires-Dist: readme-renderer==44.0
Requires-Dist: regex==2024.11.6
Requires-Dist: requests==2.32.3
Requires-Dist: requests-oauthlib==1.3.1
Requires-Dist: requests-toolbelt==1.0.0
Requires-Dist: rfc3986==2.0.0
Requires-Dist: rich==13.9.4
Requires-Dist: safetensors==0.4.5
Requires-Dist: scikit-learn==1.5.2
Requires-Dist: scipy==1.14.1
Requires-Dist: selenium==4.23.1
Requires-Dist: sentence-transformers==3.3.1
Requires-Dist: six==1.16.0
Requires-Dist: sniffio==1.3.1
Requires-Dist: sortedcontainers==2.4.0
Requires-Dist: SQLAlchemy==2.0.36
Requires-Dist: stack-data==0.6.3
Requires-Dist: sympy==1.13.1
Requires-Dist: tenacity==9.0.0
Requires-Dist: threadpoolctl==3.5.0
Requires-Dist: timm==1.0.11
Requires-Dist: tokenizers==0.20.3
Requires-Dist: tomli==2.2.1
Requires-Dist: torch==2.5.1
Requires-Dist: torchvision==0.20.1
Requires-Dist: tornado==6.4.2
Requires-Dist: tqdm==4.67.0
Requires-Dist: traitlets==5.14.3
Requires-Dist: transformers==4.46.3
Requires-Dist: trio==0.27.0
Requires-Dist: trio-websocket==0.11.1
Requires-Dist: tweepy==4.14.0
Requires-Dist: twine==6.0.1
Requires-Dist: typing-extensions==4.12.2
Requires-Dist: tzdata==2024.2
Requires-Dist: urllib3==2.2.3
Requires-Dist: wcwidth==0.2.13
Requires-Dist: websocket-client==1.8.0
Requires-Dist: wsproto==1.2.0
Requires-Dist: xxhash==3.5.0
Requires-Dist: yarl==1.17.2
Requires-Dist: zipp==3.21.0
